secure_http_server-0.0.1.dist-info/licenses/LICENSE
secure_server/__init__.py
secure_server/py.typed
secure_server/server.py
secure_server/user_manager.py
secure_http_server-0.0.1.dist-info/METADATA
secure_http_server-0.0.1.dist-info/WHEEL
secure_http_server-0.0.1.dist-info/entry_points.txt
secure_http_server-0.0.1.dist-info/top_level.txt
secure_http_server-0.0.1.dist-info/RECORD
