Metadata-Version: 2.4
Name: secure-http-server
Version: 0.0.1
Summary: A secure HTTP server with authentication and file management
Home-page: https://github.com/moncef007/secure-http-server
Author: Mohamed Elmoncef HAMDI
Author-email: mohamedelmoncef.hamdi@gmail.com
License: MIT
Project-URL: Bug Reports, https://github.com/moncef007/secure-http-server/issues
Project-URL: Source, https://github.com/moncef007/secure-http-server
Project-URL: Documentation, https://secure-http-server.readthedocs.io
Keywords: http server authentication security file-sharing
Classifier: Development Status :: 4 - Beta
Classifier: Intended Audience :: Developers
Classifier: Intended Audience :: System Administrators
Classifier: Topic :: Internet :: WWW/HTTP :: HTTP Servers
Classifier: Topic :: Security
Classifier: License :: OSI Approved :: MIT License
Classifier: Programming Language :: Python :: 3
Classifier: Programming Language :: Python :: 3.7
Classifier: Programming Language :: Python :: 3.8
Classifier: Programming Language :: Python :: 3.9
Classifier: Programming Language :: Python :: 3.10
Classifier: Programming Language :: Python :: 3.11
Classifier: Programming Language :: Python :: 3.12
Classifier: Operating System :: OS Independent
Classifier: Environment :: Console
Requires-Python: >=3.7
License-File: LICENSE
Dynamic: author
Dynamic: author-email
Dynamic: classifier
Dynamic: description
Dynamic: description-content-type
Dynamic: home-page
Dynamic: keywords
Dynamic: license
Dynamic: license-file
Dynamic: project-url
Dynamic: requires-python
Dynamic: summary
